{
  "kind": "tessa_language_page",
  "url": "http://www.open.edu/openlearncreate/course/view.php?id=2198",
  "title": "OLCreate: TESSA_ARABIC TESSA - Arabic - All Africa",
  "children": [
    {
      "kind": "subpage",
      "url": "http://www.open.edu/openlearncreate/mod/subpage/view.php?id=81251",
      "title": "OLCreate: TESSA_ARABIC: \u0645\u0647\u0627\u0631\u0627\u062a \u0627\u0644\u062d\u064a\u0627\u0629",
      "children": [
        {
          "kind": "oucontent",
          "url": "http://www.open.edu/openlearncreate/mod/oucontent/view.php?id=82912",
          "title": "OLCreate: TESSA_ARABIC \u0627\u0644\u0648\u062d\u062f\u0629 \u0631\u0642\u0645 \u0661 : \u062a\u0637\u0648\u0631 \u0627\u0644\u0634\u062e\u0635\u064a\u0629 \u2013 \u0643\u064a\u0641 \u064a\u0624\u062b\u0631 \u0627\u062d\u062a\u0631\u0627\u0645 \u0627\u0644\u0630\u0627\u062a \u0639\u0644\u0649 \u0627\u0644\u062a\u0639\u0644\u0645\u061f",
          "children": []
        },
        {
          "kind": "oucontent",
          "url": "http://www.open.edu/openlearncreate/mod/oucontent/view.php?id=84374",
          "title": "OLCreate: TESSA_ARABIC \u0627\u0644\u0642\u0633\u0645 \u0661: \u0627\u0633\u062a\u0643\u0634\u0627\u0641 \u0645\u0646 \u0647\u0645 \u062a\u0644\u0627\u0645\u064a\u0630\u0643",
          "children": []
        },
        {
          "kind": "oucontent",
          "url": "http://www.open.edu/openlearncreate/mod/oucontent/view.php?id=84375",
          "title": "OLCreate: TESSA_ARABIC \u0627\u0644\u0642\u0633\u0645 \u0662: \u062a\u062e\u0637\u064a\u0637 \u062f\u0631\u0648\u0633 \u0639\u0646 \u0627\u0644\u0646\u0645\u0648 \u0648\u0627\u0644\u062a\u0637\u0648\u0631 \u0627\u0644\u062c\u0633\u0645\u0627\u0646\u0649.",
          "children": []
        },
        {
          "kind": "oucontent",
          "url": "http://www.open.edu/openlearncreate/mod/oucontent/view.php?id=84376",
          "title": "OLCreate: TESSA_ARABIC \u0627\u0644\u0642\u0633\u0645 \u0663: \u0627\u0633\u062a\u0643\u0634\u0627\u0641 \u0627\u0641\u0643\u0627\u0631 \u0627\u0644\u062a\u0644\u0627\u0645\u064a\u0630 \u0639\u0646 \u0627\u0644\u062d\u064a\u0627\u0629 \u0627\u0644\u0635\u062d\u064a\u0629",
          "children": []
        },
        {
          "kind": "oucontent",
          "url": "http://www.open.edu/openlearncreate/mod/oucontent/view.php?id=84377",
          "title": "OLCreate: TESSA_ARABIC \u0627\u0644\u0642\u0633\u0645 \u0664: \u0627\u0644\u0646\u0634\u0627\u0637\u0627\u062a \u0627\u0644\u062a\u064a \u062a\u062f\u0639\u0645 \u0627\u0644\u0633\u0644\u0627\u0645\u0629 \u0627\u0644\u0639\u0627\u0637\u0641\u064a\u0629",
          "children": []
        },
        {
          "kind": "oucontent",
          "url": "http://www.open.edu/openlearncreate/mod/oucontent/view.php?id=84378",
          "title": "OLCreate: TESSA_ARABIC \u0627\u0644\u0642\u0633\u0645 \u0665: \u0637\u0631\u0642 \u062a\u0631\u0642\u064a\u0629 \u0627\u0644\u0633\u0639\u0627\u062f\u0629 \u0627\u0644\u0631\u0648\u062d\u064a\u0629",
          "children": []
        },
        {
          "kind": "oucontent",
          "url": "http://www.open.edu/openlearncreate/mod/oucontent/view.php?id=82911",
          "title": "OLCreate: TESSA_ARABIC \u0627\u0644\u0648\u062d\u062f\u0629 \u0631\u0642\u0645 \u0662 :\u0627\u0633\u062a\u0643\u0634\u0627\u0641 \u0627\u0644\u062a\u0637\u0648\u0631 \u0627\u0644\u0627\u062c\u062a\u0645\u0627\u0639\u0649",
          "children": []
        },
        {
          "kind": "oucontent",
          "url": "http://www.open.edu/openlearncreate/mod/oucontent/view.php?id=84379",
          "title": "OLCreate: TESSA_ARABIC \u0627\u0644\u0642\u0633\u0645 \u0661: \u0627\u0633\u062a\u0643\u0634\u0627\u0641 \u0627\u0644\u062a\u0637\u0648\u0631 \u0627\u0644\u0627\u062c\u062a\u0645\u0627\u0639\u0649",
          "children": []
        },
        {
          "kind": "oucontent",
          "url": "http://www.open.edu/openlearncreate/mod/oucontent/view.php?id=84380",
          "title": "OLCreate: TESSA_ARABIC \u0627\u0644\u0642\u0633\u0645 \u0662: \u0628\u062d\u062b \u0648\u0636\u0639 \u062a\u0644\u0627\u0645\u064a\u0630\u0643 \u0641\u064a \u0627\u0644\u0645\u062c\u062a\u0645\u0639.",
          "children": []
        },
        {
          "kind": "oucontent",
          "url": "http://www.open.edu/openlearncreate/mod/oucontent/view.php?id=84381",
          "title": "OLCreate: TESSA_ARABIC \u0627\u0644\u0642\u0633\u0645 \u0663: \u0637\u0631\u0642 \u062a\u062d\u0645\u0644 \u0627\u0644\u0645\u0633\u0626\u0648\u0644\u064a\u0629.",
          "children": []
        },
        {
          "kind": "oucontent",
          "url": "http://www.open.edu/openlearncreate/mod/oucontent/view.php?id=84382",
          "title": "OLCreate: TESSA_ARABIC \u0627\u0644\u0642\u0633\u0645 \u0664: \u0628\u062d\u062b \u0627\u062d\u062a\u0631\u0627\u0645 \u0627\u0644\u0630\u0627\u062a \u0648\u0627\u0644\u0639\u0644\u0627\u0642\u0627\u062a \u0627\u0644\u0625\u062c\u062a\u0645\u0627\u0639\u064a\u0629",
          "children": []
        },
        {
          "kind": "oucontent",
          "url": "http://www.open.edu/openlearncreate/mod/oucontent/view.php?id=84383",
          "title": "OLCreate: TESSA_ARABIC \u0627\u0644\u0642\u0633\u0645 \u0665: \u0637\u0631\u0642 \u0645\u0639\u0627\u0644\u062c\u0629 \u0627\u0644\u0646\u0632\u0627\u0639\u0627\u062a.",
          "children": []
        },
        {
          "kind": "oucontent",
          "url": "http://www.open.edu/openlearncreate/mod/oucontent/view.php?id=82913",
          "title": "OLCreate: TESSA_ARABIC \u0627\u0644\u0648\u062d\u062f\u0629 \u0631\u0642\u0645 \u0663 : \u0642\u0636\u0627\u064a\u0627 \u0627\u0644\u0645\u062c\u062a\u0645\u0639 \u0648\u0627\u0644\u0645\u0648\u0627\u0637\u0646\u0629",
          "children": []
        },
        {
          "kind": "oucontent",
          "url": "http://www.open.edu/openlearncreate/mod/oucontent/view.php?id=84384",
          "title": "OLCreate: TESSA_ARABIC \u0627\u0644\u0642\u0633\u0645 \u0661: \u0627\u0633\u062a\u0643\u0634\u0627\u0641 \u0627\u0644\u0645\u0648\u0627\u0637\u0646 \u0627\u0644\u0635\u0627\u0644\u062d.",
          "children": []
        },
        {
          "kind": "oucontent",
          "url": "http://www.open.edu/openlearncreate/mod/oucontent/view.php?id=84385",
          "title": "OLCreate: TESSA_ARABIC \u0627\u0644\u0642\u0633\u0645 \u0662: \u062a\u062e\u0637\u064a\u0637 \u062f\u0631\u0648\u0633 \u0639\u0646 \u0627\u0644\u0646\u0645\u0648 \u0648\u0627\u0644\u062a\u0637\u0648\u0631 \u0627\u0644\u062c\u0633\u0645\u0627\u0646\u0649.",
          "children": []
        },
        {
          "kind": "oucontent",
          "url": "http://www.open.edu/openlearncreate/mod/oucontent/view.php?id=84386",
          "title": "OLCreate: TESSA_ARABIC \u0627\u0644\u0642\u0633\u0645 \u0663: \u0628\u062d\u062b \u0645\u0648\u0636\u0648\u0639 \u0627\u0644\u0639\u0645\u0644 \u0648\u0627\u0644\u062a\u0648\u0638\u064a\u0641 1",
          "children": []
        },
        {
          "kind": "oucontent",
          "url": "http://www.open.edu/openlearncreate/mod/oucontent/view.php?id=84387",
          "title": "OLCreate: TESSA_ARABIC \u0627\u0644\u0642\u0633\u0645 \u0664: \u0627\u0633\u062a\u0643\u0634\u0627\u0641 \u0627\u0644\u0628\u064a\u0626\u0629",
          "children": []
        },
        {
          "kind": "oucontent",
          "url": "http://www.open.edu/openlearncreate/mod/oucontent/view.php?id=84388",
          "title": "OLCreate: TESSA_ARABIC \u0627\u0644\u0642\u0633\u0645 \u0665: \u0637\u0631\u0642 \u062d\u0633\u0627\u0633\u0629 \u0644\u0625\u062b\u0627\u0631\u0629 \u0645\u0648\u0636\u0648\u0639 \u0641\u064a\u0631\u0648\u0633 \u0646\u0642\u0635\u0627\u0646 \u0627\u0644\u0645\u0646\u0627\u0639\u0629 \u0627\u0644\u0645\u0643\u062a\u0633\u0628\u0629 / \u0627\u0644\u0627\u064a\u062f\u0632",
          "children": []
        }
      ]
    },
    {
      "kind": "subpage",
      "url": "http://www.open.edu/openlearncreate/mod/subpage/view.php?id=81252",
      "title": "OLCreate: TESSA_ARABIC: \u0627\u0644\u0623\u062f\u0628",
      "children": [
        {
          "kind": "oucontent",
          "url": "http://www.open.edu/openlearncreate/mod/oucontent/view.php?id=82908",
          "title": "OLCreate: TESSA_ARABIC \u0627\u0644\u0648\u062d\u062f\u0629 \u0631\u0642\u0645 \u0661 :\u0627\u0644\u0642\u0631\u0627\u0621\u0629 \u0648\u0627\u0644\u0643\u062a\u0627\u0628\u0629 \u0644\u0623\u063a\u0631\u0627\u0636 \u0645\u062a\u0639\u062f\u062f\u0629",
          "children": []
        },
        {
          "kind": "oucontent",
          "url": "http://www.open.edu/openlearncreate/mod/oucontent/view.php?id=84389",
          "title": "OLCreate: TESSA_ARABIC \u0627\u0644\u0642\u0633\u0645 \u0661 : \u062f\u0639\u0645 \u0648\u062a\u0642\u064a\u064a\u0645 \u0627\u0644\u0642\u0631\u0627\u0621\u0629 \u0648\u0627\u0644\u0643\u062a\u0627\u0628\u0629.",
          "children": []
        },
        {
          "kind": "oucontent",
          "url": "http://www.open.edu/openlearncreate/mod/oucontent/view.php?id=84390",
          "title": "OLCreate: TESSA_ARABIC \u0627\u0644\u0642\u0633\u0645 \u0662: \u062a\u0646\u0634\u064a\u0637 \u0627\u0644\u0631\u063a\u0628\u0629 \u0648\u062a\u062d\u0641\u064a\u0632\u0647\u0627 \u0644\u0642\u0631\u0627\u0621\u0629 \u0627\u0644\u0642\u0635\u0635.",
          "children": []
        },
        {
          "kind": "oucontent",
          "url": "http://www.open.edu/openlearncreate/mod/oucontent/view.php?id=84391",
          "title": "OLCreate: TESSA_ARABIC \u0627\u0644\u0642\u0633\u0645 \u0663: \u0637\u0631\u0642 \u0627\u0644\u0642\u0631\u0627\u0621\u0629 \u0648\u0627\u0644\u0627\u0633\u062a\u062c\u0627\u0628\u0629 \u0644\u0646\u0635\u0648\u0635 \u0627\u0644\u0645\u0639\u0644\u0648\u0645\u0627\u062a.",
          "children": []
        },
        {
          "kind": "oucontent",
          "url": "http://www.open.edu/openlearncreate/mod/oucontent/view.php?id=84392",
          "title": "OLCreate: TESSA_ARABIC \u0627\u0644\u0642\u0633\u0645 \u0664 : \u0637\u0631\u0642 \u0648\u0623\u0633\u0627\u0644\u064a\u0628 \u0644\u0639\u0631\u0636 \u0648\u062c\u0647\u0629 \u0646\u0638\u0631\u0643.",
          "children": []
        },
        {
          "kind": "oucontent",
          "url": "http://www.open.edu/openlearncreate/mod/oucontent/view.php?id=84393",
          "title": "OLCreate: TESSA_ARABIC \u0627\u0644\u0642\u0633\u0645 \u0665 : \u0623\u0646 \u062a\u0643\u0648\u0646 \u0642\u0627\u0631\u0626\u0627\u064b \u0648\u0643\u0627\u062a\u0628\u0627\u064b \u0644\u0647 \u0627\u0644\u0642\u062f\u0631\u0629 \u0639\u0644\u0649 \u0627\u0644\u0645\u0631\u0627\u062c\u0639\u0629 \u0648\u0627\u0644\u0646\u0642\u062f",
          "children": []
        },
        {
          "kind": "oucontent",
          "url": "http://www.open.edu/openlearncreate/mod/oucontent/view.php?id=82909",
          "title": "OLCreate: TESSA_ARABIC \u0627\u0644\u0648\u062d\u062f\u0629 \u0631\u0642\u0645 \u0662 :\u062a\u0648\u0638\u064a\u0641 \u0635\u0648\u062a \u0627\u0644\u0645\u062c\u062a\u0645\u0639 \u0648\u0622\u0631\u0627\u0626\u0647 \u0641\u064a \u0627\u0644\u0641\u0635\u0644 \u0627\u0644\u062f\u0631\u0627\u0633\u064a",
          "children": []
        },
        {
          "kind": "oucontent",
          "url": "http://www.open.edu/openlearncreate/mod/oucontent/view.php?id=84394",
          "title": "OLCreate: TESSA_ARABIC \u0627\u0644\u0642\u0633\u0645 \u0661 : \u0627\u0633\u062a\u0643\u0634\u0627\u0641 \u0627\u0644\u0642\u0635\u0635 \u0648\u0625\u062f\u0631\u0627\u0643\u0647\u0627",
          "children": []
        },
        {
          "kind": "oucontent",
          "url": "http://www.open.edu/openlearncreate/mod/oucontent/view.php?id=84395",
          "title": "OLCreate: TESSA_ARABIC \u0627\u0644\u0642\u0633\u0645 \u0662: \u0637\u0631\u0642 \u062c\u0645\u0639 \u0627\u0644\u0642\u0635\u0635 \u0648\u0623\u062f\u0627\u0626\u0647\u0627.",
          "children": []
        },
        {
          "kind": "oucontent",
          "url": "http://www.open.edu/openlearncreate/mod/oucontent/view.php?id=84396",
          "title": "OLCreate: TESSA_ARABIC \u0627\u0644\u0642\u0633\u0645 \u0663: \u0627\u0633\u062a\u062e\u062f\u0627\u0645 \u0627\u0644\u0623\u0644\u0639\u0627\u0628 \u0627\u0644\u0645\u062d\u0644\u064a\u0629 \u0641\u064a \u0627\u0644\u062a\u0639\u0644\u0645",
          "children": []
        },
        {
          "kind": "oucontent",
          "url": "http://www.open.edu/openlearncreate/mod/oucontent/view.php?id=84397",
          "title": "OLCreate: TESSA_ARABIC \u0627\u0644\u0642\u0633\u0645 \u0664 : \u0627\u0633\u062a\u062e\u062f\u0627\u0645 \u0627\u0644\u0642\u0635\u0635 \u0648\u0627\u0644\u0634\u0639\u0631",
          "children": []
        },
        {
          "kind": "oucontent",
          "url": "http://www.open.edu/openlearncreate/mod/oucontent/view.php?id=84398",
          "title": "OLCreate: TESSA_ARABIC \u0627\u0644\u0642\u0633\u0645 \u0665 : \u062a\u062d\u0648\u064a\u0644 \u0627\u0644\u0642\u0635\u0635 \u0648\u0627\u0644\u0642\u0635\u0627\u0626\u062f \u0648\u0627\u0644\u0623\u0644\u0639\u0627\u0628 \u0627\u0644\u0634\u0641\u0627\u0647\u064a\u0629 \u0625\u0644\u0649 \u0643\u062a\u0628",
          "children": []
        },
        {
          "kind": "oucontent",
          "url": "http://www.open.edu/openlearncreate/mod/oucontent/view.php?id=82910",
          "title": "OLCreate: TESSA_ARABIC \u0627\u0644\u0648\u062d\u062f\u0629 \u0631\u0642\u0645 \u0663 : \u062a\u0646\u0645\u064a\u0629 \u0627\u0644\u062a\u0648\u0627\u0635\u0644 \u0628\u0627\u0644\u0644\u063a\u0629 \u0627\u0644\u0625\u0636\u0627\u0641\u064a\u0629",
          "children": []
        },
        {
          "kind": "oucontent",
          "url": "http://www.open.edu/openlearncreate/mod/oucontent/view.php?id=84399",
          "title": "OLCreate: TESSA_ARABIC \u0627\u0644\u0642\u0633\u0645 \u0661 : \u062a\u0647\u064a\u0626\u0629 \u0627\u0644\u0638\u0631\u0648\u0641 \u0627\u0644\u0637\u0628\u064a\u0639\u064a\u0629 \u0644\u0645\u0645\u0627\u0631\u0633\u0629 \u0627\u0644\u0644\u063a\u0629",
          "children": []
        },
        {
          "kind": "oucontent",
          "url": "http://www.open.edu/openlearncreate/mod/oucontent/view.php?id=84400",
          "title": "OLCreate: TESSA_ARABIC \u0627\u0644\u0642\u0633\u0645 \u0662: \u0648\u0633\u0627\u0626\u0644 \u0644\u062a\u062d\u0642\u064a\u0642 \u0627\u0644\u0637\u0644\u0627\u0642\u0629 \u0648\u0627\u0644\u062f\u0642\u0629",
          "children": []
        },
        {
          "kind": "oucontent",
          "url": "http://www.open.edu/openlearncreate/mod/oucontent/view.php?id=84401",
          "title": "OLCreate: TESSA_ARABIC \u0627\u0644\u0642\u0633\u0645 \u0663: \u062e\u0644\u0642 \u0641\u0631\u0635 \u0644\u0644\u062a\u0648\u0627\u0635\u0644",
          "children": []
        },
        {
          "kind": "oucontent",
          "url": "http://www.open.edu/openlearncreate/mod/oucontent/view.php?id=84402",
          "title": "OLCreate: TESSA_ARABIC \u0627\u0644\u0642\u0633\u0645 \u0664 : \u0623\u0633\u0627\u0644\u064a\u0628 \u0644\u062a\u0648\u0638\u064a\u0641 \u0645\u0639\u0627\u0631\u0641 \u0627\u0644\u0644\u063a\u0629 \u0627\u0644\u0645\u062d\u0644\u064a\u0629.",
          "children": []
        },
        {
          "kind": "oucontent",
          "url": "http://www.open.edu/openlearncreate/mod/oucontent/view.php?id=84403",
          "title": "OLCreate: TESSA_ARABIC \u0627\u0644\u0642\u0633\u0645 \u0665 : \u0628\u0646\u0627\u0621 \u0639\u0644\u0627\u0642\u0627\u062a \u062a\u0633\u0627\u0646\u062f \u0628\u0627\u0644\u0644\u063a\u0629 \u0627\u0644\u0625\u0636\u0627\u0641\u064a\u0629",
          "children": []
        }
      ]
    },
    {
      "kind": "subpage",
      "url": "http://www.open.edu/openlearncreate/mod/subpage/view.php?id=81253",
      "title": "OLCreate: TESSA_ARABIC: \u0627\u0644\u0631\u064a\u0627\u0636\u064a\u0627\u062a",
      "children": [
        {
          "kind": "oucontent",
          "url": "http://www.open.edu/openlearncreate/mod/oucontent/view.php?id=82907",
          "title": "OLCreate: TESSA_ARABIC \u0627\u0644\u0648\u062d\u062f\u0629 \u0631\u0642\u0645 \u0661 :\u0627\u0644\u062a\u0642\u0635\u0651\u064a \u0641\u064a \u0627\u0644\u0639\u062f\u062f \u0648 \u0627\u0644\u0646\u0645\u0637",
          "children": []
        },
        {
          "kind": "oucontent",
          "url": "http://www.open.edu/openlearncreate/mod/oucontent/view.php?id=84404",
          "title": "OLCreate: TESSA_ARABIC \u0627\u0644\u0642\u0633\u0645 \u0661 : \u0627\u0644\u062a\u0639\u0644\u0645 \u0645\u0646 \u062e\u0644\u0627\u0644 \u0627\u0644\u0623\u0644\u0639\u0627\u0628.",
          "children": []
        },
        {
          "kind": "oucontent",
          "url": "http://www.open.edu/openlearncreate/mod/oucontent/view.php?id=84405",
          "title": "OLCreate: TESSA_ARABIC \u0627\u0644\u0642\u0633\u0645 \u0662: \u0627\u0644\u0627\u0646\u0645\u0627\u0637 \u0641\u064a \u0627\u0644\u0631\u0633\u0645 \u0627\u0644\u0628\u064a\u0627\u0646\u064a \u0644\u0644\u0631\u0642\u0645.",
          "children": []
        },
        {
          "kind": "oucontent",
          "url": "http://www.open.edu/openlearncreate/mod/oucontent/view.php?id=84406",
          "title": "OLCreate: TESSA_ARABIC \u0627\u0644\u0642\u0633\u0645 \u0663: \u0648\u0633\u0627\u0626\u0644 \u062d\u0644 \u0627\u0644\u0645\u0633\u0627\u0626\u0644 \u0627\u0644\u0631\u064a\u0627\u0636\u064a\u0629.",
          "children": []
        },
        {
          "kind": "oucontent",
          "url": "http://www.open.edu/openlearncreate/mod/oucontent/view.php?id=84407",
          "title": "OLCreate: TESSA_ARABIC \u0627\u0644\u0642\u0633\u0645 \u0664 : \u0631\u0624\u064a\u0629 \u0639\u0645\u0644\u064a\u0629 \u0627\u0644\u0636\u0631\u0628.",
          "children": []
        },
        {
          "kind": "oucontent",
          "url": "http://www.open.edu/openlearncreate/mod/oucontent/view.php?id=84408",
          "title": "OLCreate: TESSA_ARABIC \u0627\u0644\u0642\u0633\u0645 \u0665 : \u0639\u0645\u0644 \u0639\u0645\u0644\u064a \u0628\u0627\u0633\u062a\u062e\u062f\u0627\u0645 \u0623\u0634\u0631\u0637\u0629 \u0648 \u0623\u0642\u0631\u0627\u0635 \u0627\u0644\u0643\u0633\u0648\u0631.",
          "children": []
        },
        {
          "kind": "oucontent",
          "url": "http://www.open.edu/openlearncreate/mod/oucontent/view.php?id=82906",
          "title": "OLCreate: TESSA_ARABIC \u0627\u0644\u0648\u062d\u062f\u0629 \u0631\u0642\u0645 \u0662 :\u0627\u0644\u062a\u0642\u0635\u064a \u0641\u064a \u0627\u0644\u0634\u0643\u0644 \u0648 \u0627\u0644\u0641\u0631\u0627\u063a",
          "children": []
        },
        {
          "kind": "oucontent",
          "url": "http://www.open.edu/openlearncreate/mod/oucontent/view.php?id=84409",
          "title": "OLCreate: TESSA_ARABIC \u0627\u0644\u0642\u0633\u0645 \u0661 : \u0625\u0633\u062a\u0643\u0634\u0627\u0641 \u0627\u0644\u0623\u0634\u0643\u0627\u0644.",
          "children": []
        },
        {
          "kind": "oucontent",
          "url": "http://www.open.edu/openlearncreate/mod/oucontent/view.php?id=84410",
          "title": "OLCreate: TESSA_ARABIC \u0627\u0644\u0642\u0633\u0645 \u0662: \u0637\u0631\u0642 \u0639\u0645\u0644\u064a\u0629 \u0644\u0635\u0646\u0639 \u0645\u0643\u0639\u0628 \u0645\u0646 \u0648\u0631\u0642\u0629.",
          "children": []
        },
        {
          "kind": "oucontent",
          "url": "http://www.open.edu/openlearncreate/mod/oucontent/view.php?id=84411",
          "title": "OLCreate: TESSA_ARABIC \u0627\u0644\u0642\u0633\u0645 \u0663: \u0627\u0643\u062a\u0634\u0627\u0641 \u0627\u0644\u0647\u0646\u062f\u0633\u0629 \u062b\u0644\u0627\u062b\u064a\u0629 \u0627\u0644\u0623\u0628\u0639\u0627\u062f.",
          "children": []
        },
        {
          "kind": "oucontent",
          "url": "http://www.open.edu/openlearncreate/mod/oucontent/view.php?id=84412",
          "title": "OLCreate: TESSA_ARABIC \u0627\u0644\u0642\u0633\u0645 \u0664 : \u0627\u0633\u062a\u0643\u0634\u0627\u0641 \u0627\u0644\u062a\u0646\u0627\u0638\u0631.",
          "children": []
        },
        {
          "kind": "oucontent",
          "url": "http://www.open.edu/openlearncreate/mod/oucontent/view.php?id=84413",
          "title": "OLCreate: TESSA_ARABIC \u0627\u0644\u0642\u0633\u0645 \u0665 : \u062a\u0639\u0644\u064a\u0645 \u0627\u0644\u062a\u062d\u0648\u0644\u0627\u062a.",
          "children": []
        },
        {
          "kind": "oucontent",
          "url": "http://www.open.edu/openlearncreate/mod/oucontent/view.php?id=82905",
          "title": "OLCreate: TESSA_ARABIC \u0627\u0644\u0648\u062d\u062f\u0629 \u0631\u0642\u0645 \u0663 : \u0627\u0633\u062a\u0643\u0634\u0627\u0641 \u0627\u0644\u0642\u064a\u0627\u0633\u0627\u062a \u0648\u0645\u0639\u0627\u0644\u062c\u0629 \u0627\u0644\u0628\u064a\u0627\u0646\u0627\u062a",
          "children": []
        },
        {
          "kind": "oucontent",
          "url": "http://www.open.edu/openlearncreate/mod/oucontent/view.php?id=84414",
          "title": "OLCreate: TESSA_ARABIC \u0627\u0644\u0642\u0633\u0645 \u0661 : \u062a\u0639\u0631\u064a\u0641 \u0627\u0644\u0642\u064a\u0627\u0633\u0627\u062a",
          "children": []
        },
        {
          "kind": "oucontent",
          "url": "http://www.open.edu/openlearncreate/mod/oucontent/view.php?id=84415",
          "title": "OLCreate: TESSA_ARABIC \u0627\u0644\u0642\u0633\u0645 \u0662: \u0627\u0644\u0642\u064a\u0627\u0633 \u0648\u0645\u0639\u0627\u0644\u062c\u0629 \u0627\u0644\u0648\u0642\u062a.",
          "children": []
        },
        {
          "kind": "oucontent",
          "url": "http://www.open.edu/openlearncreate/mod/oucontent/view.php?id=84416",
          "title": "OLCreate: TESSA_ARABIC \u0627\u0644\u0642\u0633\u0645 \u0663: \u0645\u0646\u0627\u0642\u0634\u0629 \u0627\u0644\u0628\u064a\u0627\u0646\u0627\u062a",
          "children": []
        },
        {
          "kind": "oucontent",
          "url": "http://www.open.edu/openlearncreate/mod/oucontent/view.php?id=84417",
          "title": "OLCreate: TESSA_ARABIC \u0627\u0644\u0642\u0633\u0645 \u0664 : \u0627\u0644\u0639\u0645\u0644 \u0645\u0639 \u0627\u0644\u0623\u0648\u0632\u0627\u0646",
          "children": []
        },
        {
          "kind": "oucontent",
          "url": "http://www.open.edu/openlearncreate/mod/oucontent/view.php?id=84418",
          "title": "OLCreate: TESSA_ARABIC \u0627\u0644\u0642\u0633\u0645 \u0665 : \u0627\u0644\u0639\u0645\u0644 \u0645\u0639 \u0627\u0644\u0645\u0633\u0627\u0641\u0629",
          "children": []
        }
      ]
    },
    {
      "kind": "subpage",
      "url": "http://www.open.edu/openlearncreate/mod/subpage/view.php?id=81254",
      "title": "OLCreate: TESSA_ARABIC: \u0627\u0644\u0639\u0644\u0648\u0645",
      "children": [
        {
          "kind": "oucontent",
          "url": "http://www.open.edu/openlearncreate/mod/oucontent/view.php?id=82904",
          "title": "OLCreate: TESSA_ARABIC \u0627\u0644\u0648\u062d\u062f\u0629 \u0631\u0642\u0645 \u0661 :\u0627\u0644\u0646\u0638\u0631 \u0641\u064a \u0627\u0644\u062d\u064a\u0627\u0629",
          "children": []
        },
        {
          "kind": "oucontent",
          "url": "http://www.open.edu/openlearncreate/mod/oucontent/view.php?id=84419",
          "title": "OLCreate: TESSA_ARABIC \u0627\u0644\u0642\u0633\u0645 \u0661:\u062a\u0635\u0646\u064a\u0641 \u0627\u0644\u0643\u0627\u0626\u0646\u0627\u062a \u0627\u0644\u062d\u064a\u0629",
          "children": []
        },
        {
          "kind": "oucontent",
          "url": "http://www.open.edu/openlearncreate/mod/oucontent/view.php?id=84420",
          "title": "OLCreate: TESSA_ARABIC \u0627\u0644\u0642\u0633\u0645 \u0662:\u0646\u0638\u0631\u0629 \u0641\u0627\u062d\u0635\u0629 \u0644\u0644\u0646\u0628\u0627\u062a\u0627\u062a.",
          "children": []
        },
        {
          "kind": "oucontent",
          "url": "http://www.open.edu/openlearncreate/mod/oucontent/view.php?id=84421",
          "title": "OLCreate: TESSA_ARABIC \u0627\u0644\u0642\u0633\u0645 \u0663 :\u0641\u062d\u0635 \u0627\u0644\u062d\u064a\u0648\u0627\u0646\u0627\u062a: \u0627\u0644\u0635\u0627\u0626\u062f\u0629 \u0648\u0627\u0644\u0645\u0635\u064a\u062f\u0629 \u0627\u0644\u0645\u0641\u062a\u0631\u0633\u0627\u062a \u0648\u0627\u0644\u0641\u0631\u0627\u0626\u0633",
          "children": []
        },
        {
          "kind": "oucontent",
          "url": "http://www.open.edu/openlearncreate/mod/oucontent/view.php?id=84422",
          "title": "OLCreate: TESSA_ARABIC \u0627\u0644\u0642\u0633\u0645 \u0664: \u0627\u0633\u062a\u0646\u062a\u0627\u062c \u0643\u064a\u0641\u064a\u0629 \u062a\u0643\u064a\u0641 \u0627\u0644\u0646\u0628\u0627\u062a\u0627\u062a \u0648\u0627\u0644\u062d\u064a\u0648\u0627\u0646\u0627\u062a",
          "children": []
        },
        {
          "kind": "oucontent",
          "url": "http://www.open.edu/openlearncreate/mod/oucontent/view.php?id=84423",
          "title": "OLCreate: TESSA_ARABIC \u0627\u0644\u0642\u0633\u0645 \u0665: \u0665:\u0645\u0648\u0627\u0642\u0641 \u0645\u062a\u0637\u0648\u0631\u0629 \u062d\u0648\u0644 \u062a\u0627\u062b\u064a\u0631\u0646\u0627 \u0627\u0644\u0628\u064a\u0626\u064a",
          "children": []
        },
        {
          "kind": "oucontent",
          "url": "http://www.open.edu/openlearncreate/mod/oucontent/view.php?id=84513",
          "title": "OLCreate: TESSA_ARABIC \u0627\u0644\u0648\u062d\u062f\u0629 \u0631\u0642\u0645 \u0662 :\u0627\u0644\u0628\u062d\u062b \u0641\u064a \u0637\u0628\u064a\u0639\u0629 \u0627\u0644\u0645\u0648\u0627\u062f",
          "children": []
        },
        {
          "kind": "oucontent",
          "url": "http://www.open.edu/openlearncreate/mod/oucontent/view.php?id=84517",
          "title": "OLCreate: TESSA_ARABIC \u0627\u0644\u0642\u0633\u0645 \u0661: \u0648\u0635\u0641 \u0648\u062a\u0635\u0646\u064a\u0641 \u0627\u0644\u0645\u0648\u0627\u062f.",
          "children": []
        },
        {
          "kind": "oucontent",
          "url": "http://www.open.edu/openlearncreate/mod/oucontent/view.php?id=84515",
          "title": "OLCreate: TESSA_ARABIC \u0627\u0644\u0642\u0633\u0645 \u0662:\u0627\u0633\u062a\u0643\u0634\u0627\u0641 \u0627\u0644\u0645\u0648\u0627\u062f \u0627\u0644\u0635\u0644\u0628\u0629",
          "children": []
        },
        {
          "kind": "oucontent",
          "url": "http://www.open.edu/openlearncreate/mod/oucontent/view.php?id=84514",
          "title": "OLCreate: TESSA_ARABIC \u0627\u0644\u0642\u0633\u0645 \u0663: \u0627\u0644\u0646\u0638\u0631 \u0641\u064a \u0627\u0644\u0633\u0648\u0627\u0626\u0644",
          "children": []
        },
        {
          "kind": "oucontent",
          "url": "http://www.open.edu/openlearncreate/mod/oucontent/view.php?id=84516",
          "title": "OLCreate: TESSA_ARABIC \u0627\u0644\u0642\u0633\u0645 \u0664: \u0627\u0644\u0647\u0648\u0627\u0621 \u2013 \u0623\u064a\u0646\u061f \u0644\u0645\u0627\u0630\u0627\u061f",
          "children": []
        },
        {
          "kind": "oucontent",
          "url": "http://www.open.edu/openlearncreate/mod/oucontent/view.php?id=84428",
          "title": "OLCreate: TESSA_ARABIC \u0627\u0644\u0642\u0633\u0645 \u0665: \u0627\u0644\u062d\u0643\u0645\u0629 \u0641\u064a \u0627\u0633\u062a\u0639\u0645\u0627\u0644 \u0648\u0627\u0639\u0627\u062f\u0629 \u0627\u0633\u062a\u0639\u0645\u0627\u0644 \u0627\u0644\u0645\u0648\u0627\u062f.",
          "children": []
        },
        {
          "kind": "oucontent",
          "url": "http://www.open.edu/openlearncreate/mod/oucontent/view.php?id=82902",
          "title": "OLCreate: TESSA_ARABIC \u0627\u0644\u0648\u062d\u062f\u0629 \u0631\u0642\u0645 \u0663 : \u0627\u0644\u0637\u0627\u0642\u0629 \u0648\u0627\u0644\u062d\u0631\u0643\u0629",
          "children": []
        },
        {
          "kind": "oucontent",
          "url": "http://www.open.edu/openlearncreate/mod/oucontent/view.php?id=84430",
          "title": "OLCreate: TESSA_ARABIC \u0627\u0644\u0642\u0633\u0645 \u0661:\u0627\u0644\u0642\u0648\u0649 \u0627\u0644\u064a\u0648\u0645\u064a\u0629 \u2013 \u0641\u062d\u0635 \u0627\u0644\u062d\u0631\u0643\u0629",
          "children": []
        },
        {
          "kind": "oucontent",
          "url": "http://www.open.edu/openlearncreate/mod/oucontent/view.php?id=84431",
          "title": "OLCreate: TESSA_ARABIC \u0627\u0644\u0642\u0633\u0645 \u0662: \u0628\u062d\u062b \u0627\u0644\u0623\u0635\u0648\u0627\u062a \u0648\u0627\u0644\u0645\u0648\u0633\u064a\u0642\u0649",
          "children": []
        },
        {
          "kind": "oucontent",
          "url": "http://www.open.edu/openlearncreate/mod/oucontent/view.php?id=84432",
          "title": "OLCreate: TESSA_ARABIC \u0627\u0644\u0642\u0633\u0645 \u0663 : \u0641\u062d\u0635 \u0627\u0644\u0643\u0647\u0631\u0628\u0627\u0621",
          "children": []
        },
        {
          "kind": "oucontent",
          "url": "http://www.open.edu/openlearncreate/mod/oucontent/view.php?id=84433",
          "title": "OLCreate: TESSA_ARABIC \u0627\u0644\u0642\u0633\u0645 \u0664: \u0627\u0644\u0646\u0638\u0631 \u0625\u0644\u0649 \u0627\u0644\u0636\u0648\u0621 \u0648\u0627\u0644\u0638\u0644",
          "children": []
        },
        {
          "kind": "oucontent",
          "url": "http://www.open.edu/openlearncreate/mod/oucontent/view.php?id=84429",
          "title": "OLCreate: TESSA_ARABIC \u0627\u0644\u0642\u0633\u0645 \u0665: \u0645\u0646 \u0627\u0644\u0623\u0631\u0636 \u0625\u0644\u0649 \u0627\u0644\u0646\u062c\u0648\u0645 \u2013 \u0628\u0627\u0633\u062a\u062e\u062f\u0627\u0645 \u0627\u0644\u0646\u0645\u0627\u0630\u062c",
          "children": []
        }
      ]
    },
    {
      "kind": "subpage",
      "url": "http://www.open.edu/openlearncreate/mod/subpage/view.php?id=81255",
      "title": "OLCreate: TESSA_ARABIC: \u0627\u0644\u062f\u0631\u0627\u0633\u0627\u062a \u0627\u0644\u0627\u062c\u062a\u0645\u0627\u0639\u064a\u0629 \u0648\u0627\u0644\u0622\u062f\u0627\u0628",
      "children": [
        {
          "kind": "oucontent",
          "url": "http://www.open.edu/openlearncreate/mod/oucontent/view.php?id=82901",
          "title": "OLCreate: TESSA_ARABIC \u0627\u0644\u0648\u062d\u062f\u0629 \u0631\u0642\u0645 \u0661 :\u062a\u0646\u0645\u064a\u0629 \u0641\u0647\u0645 \u0627\u0644\u0645\u0643\u0627\u0646",
          "children": []
        },
        {
          "kind": "oucontent",
          "url": "http://www.open.edu/openlearncreate/mod/oucontent/view.php?id=84444",
          "title": "OLCreate: TESSA_ARABIC \u0627\u0644\u0642\u0633\u0645 \u0661:\u0631\u0633\u0645 \u062e\u0631\u064a\u0637\u0629 \u0627\u0644\u0628\u064a\u0626\u0629 \u0627\u0644\u0645\u062d\u0644\u064a\u0629.",
          "children": []
        },
        {
          "kind": "oucontent",
          "url": "http://www.open.edu/openlearncreate/mod/oucontent/view.php?id=84445",
          "title": "OLCreate: TESSA_ARABIC \u0627\u0644\u0642\u0633\u0645 \u0662:\u0627\u0644\u0645\u0648\u0627\u0631\u062f \u0648\u0627\u0644\u0645\u0633\u062a\u0648\u0637\u0646\u0627\u062a \u0627\u0644\u0628\u0634\u0631\u064a\u0629.",
          "children": []
        },
        {
          "kind": "oucontent",
          "url": "http://www.open.edu/openlearncreate/mod/oucontent/view.php?id=84446",
          "title": "OLCreate: TESSA_ARABIC \u0627\u0644\u0642\u0633\u0645 \u0663: \u0645\u0639\u0631\u0641\u0629 \u0627\u0644\u0637\u0642\u0633.",
          "children": []
        },
        {
          "kind": "oucontent",
          "url": "http://www.open.edu/openlearncreate/mod/oucontent/view.php?id=84447",
          "title": "OLCreate: TESSA_ARABIC \u0627\u0644\u0642\u0633\u0645 \u0664:\u0628\u062d\u062b \u0641\u0649 \u0627\u0644\u0628\u064a\u0626\u0627\u062a \u0627\u0644\u0645\u062a\u063a\u064a\u0631\u0629.",
          "children": []
        },
        {
          "kind": "oucontent",
          "url": "http://www.open.edu/openlearncreate/mod/oucontent/view.php?id=84448",
          "title": "OLCreate: TESSA_ARABIC \u0627\u0644\u0642\u0633\u0645 \u0665:\u0641\u062d\u0635 \u0627\u0645\u0627\u0643\u0646 \u0648\u0646\u0627\u0633 \u0622\u062e\u0631\u064a\u0646.",
          "children": []
        },
        {
          "kind": "oucontent",
          "url": "http://www.open.edu/openlearncreate/mod/oucontent/view.php?id=82900",
          "title": "OLCreate: TESSA_ARABIC \u0627\u0644\u0648\u062d\u062f\u0629 \u0631\u0642\u0645 \u0662 :\u0641\u062d\u0635 \u0627\u0644\u062a\u0627\u0631\u064a\u062e",
          "children": []
        },
        {
          "kind": "oucontent",
          "url": "http://www.open.edu/openlearncreate/mod/oucontent/view.php?id=84434",
          "title": "OLCreate: TESSA_ARABIC \u0627\u0644\u0642\u0633\u0645 \u0661: \u0641\u062d\u0635 \u062a\u0627\u0631\u064a\u062e \u0627\u0644\u0639\u0627\u0626\u0644\u0629.",
          "children": []
        },
        {
          "kind": "oucontent",
          "url": "http://www.open.edu/openlearncreate/mod/oucontent/view.php?id=84435",
          "title": "OLCreate: TESSA_ARABIC \u0627\u0644\u0642\u0633\u0645 \u0662: \u0641\u062d\u0635 \u0637\u0631\u064a\u0642\u0629 \u0639\u064a\u0634\u0646\u0627",
          "children": []
        },
        {
          "kind": "oucontent",
          "url": "http://www.open.edu/openlearncreate/mod/oucontent/view.php?id=84436",
          "title": "OLCreate: TESSA_ARABIC \u0627\u0644\u0642\u0633\u0645 \u0663: \u0627\u0633\u062a\u062e\u062f\u0627\u0645 \u0645\u062e\u062a\u0644\u0641 \u0623\u0634\u0643\u0627\u0644 \u0627\u0644\u0628\u064a\u0646\u0627\u062a \u0644\u062f\u0631\u0627\u0633\u0629 \u0627\u0644\u0645\u062c\u062a\u0645\u0639\u0627\u062a \u0627\u0644\u0623\u0641\u0631\u064a\u0642\u064a\u0629 \u0627\u0644\u0642\u062f\u064a\u0645\u0629",
          "children": []
        },
        {
          "kind": "oucontent",
          "url": "http://www.open.edu/openlearncreate/mod/oucontent/view.php?id=84437",
          "title": "OLCreate: TESSA_ARABIC \u0627\u0644\u0642\u0633\u0645 \u0664: \u0641\u0647\u0645 \u0627\u0644\u062e\u0637\u0648\u0637 \u0627\u0644\u0632\u0645\u0646\u064a\u0629",
          "children": []
        },
        {
          "kind": "oucontent",
          "url": "http://www.open.edu/openlearncreate/mod/oucontent/view.php?id=84438",
          "title": "OLCreate: TESSA_ARABIC \u0627\u0644\u0642\u0633\u0645 \u0665: \u0627\u0633\u062a\u062e\u062f\u0627\u0645 \u0627\u0644\u0645\u0635\u0646\u0648\u0639\u0627\u062a \u0627\u0644\u064a\u062f\u0648\u064a\u0629 \u0644\u0627\u0633\u062a\u0643\u0634\u0627\u0641 \u0627\u0644\u0645\u0627\u0636\u064a",
          "children": []
        },
        {
          "kind": "oucontent",
          "url": "http://www.open.edu/openlearncreate/mod/oucontent/view.php?id=82899",
          "title": "OLCreate: TESSA_ARABIC \u0627\u0644\u0648\u062d\u062f\u0629 \u0631\u0642\u0645 \u0663 : \u0646\u0638\u0631\u0629 \u0639\u0644\u0649 \u0627\u0644\u0641\u0646\u0648\u0646 \u0627\u0644\u062c\u0645\u064a\u0644\u0629",
          "children": []
        },
        {
          "kind": "oucontent",
          "url": "http://www.open.edu/openlearncreate/mod/oucontent/view.php?id=84439",
          "title": "OLCreate: TESSA_ARABIC \u0627\u0644\u0642\u0633\u0645 \u0661: \u0627\u0644\u062a\u0639\u0631\u0641 \u0639\u0644\u0649 \u0627\u0644\u0641\u0646\u0648\u0646 \u0627\u0644\u0645\u0631\u0626\u064a\u0629",
          "children": []
        },
        {
          "kind": "oucontent",
          "url": "http://www.open.edu/openlearncreate/mod/oucontent/view.php?id=84440",
          "title": "OLCreate: TESSA_ARABIC \u0627\u0644\u0642\u0633\u0645 \u0662: \u0627\u0644\u0628\u062d\u062b \u0648\u0627\u0644\u0623\u0639\u0645\u0627\u0644 \u0627\u0644\u064a\u062f\u0648\u064a\u0629",
          "children": []
        },
        {
          "kind": "oucontent",
          "url": "http://www.open.edu/openlearncreate/mod/oucontent/view.php?id=84441",
          "title": "OLCreate: TESSA_ARABIC \u0627\u0644\u0642\u0633\u0645 \u0663: \u0627\u0633\u062a\u062e\u062f\u0627\u0645 \u0627\u0644\u0631\u0642\u0635",
          "children": []
        },
        {
          "kind": "oucontent",
          "url": "http://www.open.edu/openlearncreate/mod/oucontent/view.php?id=84442",
          "title": "OLCreate: TESSA_ARABIC \u0627\u0644\u0642\u0633\u0645 \u0664: \u0623\u0633\u0627\u0644\u064a\u0628 \u0627\u0633\u062a\u062e\u062f\u0627\u0645 \u0627\u0644\u0645\u0648\u0633\u064a\u0642\u0649 \u0641\u064a \u063a\u0631\u0641\u0629 \u0627\u0644\u062f\u0631\u0627\u0633\u0629",
          "children": []
        },
        {
          "kind": "oucontent",
          "url": "http://www.open.edu/openlearncreate/mod/oucontent/view.php?id=84443",
          "title": "OLCreate: TESSA_ARABIC \u0627\u0644\u0642\u0633\u0645 \u0665: \u0641\u0646 \u0633\u0631\u062f \u0627\u0644\u0642\u0635\u0635",
          "children": []
        }
      ]
    },
    {
      "kind": "subpage",
      "url": "http://www.open.edu/openlearncreate/mod/subpage/view.php?id=81257",
      "title": "OLCreate: TESSA_ARABIC: \u0635\u0641\u062d\u0629 \u0645\u0627\u062f\u0629 \u0627\u0644\u0639\u0644\u0648\u0645 \u0644\u0644\u0645\u0631\u062d\u0644\u0629 \u0627\u0644\u062b\u0627\u0646\u0648\u064a\u0629",
      "children": []
    },
    {
      "kind": "subpage",
      "url": "http://www.open.edu/openlearncreate/mod/subpage/view.php?id=81256",
      "title": "OLCreate: TESSA_ARABIC: \u0645\u0648\u0627\u0631\u062f \u0631\u0626\u064a\u0633\u064a\u0629 \u0644\u0644\u0645\u0639\u0644\u0645\u064a\u0646 \u0648\u0627\u0644\u0645\u0633\u0624\u0648\u0644\u064a\u0646 \u0639\u0646 \u062a\u0639\u0644\u064a\u0645\u0647\u0645",
      "children": [
        {
          "kind": "oucontent",
          "url": "http://www.open.edu/openlearncreate/mod/oucontent/view.php?id=80312",
          "title": "OLCreate: TESSA_Eng Key Resources (All)",
          "children": [],
          "original_url": "http://www.open.edu/openlearnworks/mod/oucontent/view.php?id=80312"
        },
        {
          "kind": "oucontent",
          "url": "http://www.open.edu/openlearncreate/mod/oucontent/view.php?id=80315",
          "title": "OLCreate: TESSA_Eng Introducing the TESSA Key Resources",
          "children": [],
          "original_url": "http://www.open.edu/openlearnworks/mod/oucontent/view.php?id=80315"
        },
        {
          "kind": "oucontent",
          "url": "http://www.open.edu/openlearncreate/mod/oucontent/view.php?id=80316",
          "title": "OLCreate: TESSA_Eng Key Resource: Assessing learning",
          "children": [],
          "original_url": "http://www.open.edu/openlearnworks/mod/oucontent/view.php?id=80316"
        },
        {
          "kind": "oucontent",
          "url": "http://www.open.edu/openlearncreate/mod/oucontent/view.php?id=80317",
          "title": "OLCreate: TESSA_Eng Key Resource: Using mind maps and brainstorming to explore ideas",
          "children": [],
          "original_url": "http://www.open.edu/openlearnworks/mod/oucontent/view.php?id=80317"
        },
        {
          "kind": "oucontent",
          "url": "http://www.open.edu/openlearncreate/mod/oucontent/view.php?id=80318",
          "title": "OLCreate: TESSA_Eng Key Resource: Being a resourceful teacher in challenging circumstances",
          "children": [],
          "original_url": "http://www.open.edu/openlearnworks/mod/oucontent/view.php?id=80318"
        },
        {
          "kind": "oucontent",
          "url": "http://www.open.edu/openlearncreate/mod/oucontent/view.php?id=80319",
          "title": "OLCreate: TESSA_Eng Key Resource: Using explaining and demonstrating to assist learning",
          "children": [],
          "original_url": "http://www.open.edu/openlearnworks/mod/oucontent/view.php?id=80319"
        },
        {
          "kind": "oucontent",
          "url": "http://www.open.edu/openlearncreate/mod/oucontent/view.php?id=80320",
          "title": "OLCreate: TESSA_Eng Key Resource: Using group work in your classroom",
          "children": [],
          "original_url": "http://www.open.edu/openlearnworks/mod/oucontent/view.php?id=80320"
        },
        {
          "kind": "oucontent",
          "url": "http://www.open.edu/openlearncreate/mod/oucontent/view.php?id=80321",
          "title": "OLCreate: TESSA_Eng Key Resource: Using investigations in the classroom",
          "children": [],
          "original_url": "http://www.open.edu/openlearnworks/mod/oucontent/view.php?id=80321"
        },
        {
          "kind": "oucontent",
          "url": "http://www.open.edu/openlearncreate/mod/oucontent/view.php?id=80322",
          "title": "OLCreate: TESSA_Eng Key Resource: Tools for planning and carrying out investigations in Science",
          "children": [],
          "original_url": "http://www.open.edu/openlearnworks/mod/oucontent/view.php?id=80322"
        },
        {
          "kind": "oucontent",
          "url": "http://www.open.edu/openlearncreate/mod/oucontent/view.php?id=80323",
          "title": "OLCreate: TESSA_Eng Key Resource: Working with large classes",
          "children": [],
          "original_url": "http://www.open.edu/openlearnworks/mod/oucontent/view.php?id=80323"
        },
        {
          "kind": "oucontent",
          "url": "http://www.open.edu/openlearncreate/mod/oucontent/view.php?id=80324",
          "title": "OLCreate: TESSA_Eng Key Resource: Using the local community/environment as a resource",
          "children": [],
          "original_url": "http://www.open.edu/openlearnworks/mod/oucontent/view.php?id=80324"
        },
        {
          "kind": "oucontent",
          "url": "http://www.open.edu/openlearncreate/mod/oucontent/view.php?id=80325",
          "title": "OLCreate: TESSA_Eng Key Resource: Planning and preparing your lessons",
          "children": [],
          "original_url": "http://www.open.edu/openlearnworks/mod/oucontent/view.php?id=80325"
        },
        {
          "kind": "oucontent",
          "url": "http://www.open.edu/openlearncreate/mod/oucontent/view.php?id=80326",
          "title": "OLCreate: TESSA_Eng Key Resource: Using questioning to promote thinking",
          "children": [],
          "original_url": "http://www.open.edu/openlearnworks/mod/oucontent/view.php?id=80326"
        },
        {
          "kind": "oucontent",
          "url": "http://www.open.edu/openlearncreate/mod/oucontent/view.php?id=80327",
          "title": "OLCreate: TESSA_Eng Key Resource: Researching in the classroom",
          "children": [],
          "original_url": "http://www.open.edu/openlearnworks/mod/oucontent/view.php?id=80327"
        },
        {
          "kind": "oucontent",
          "url": "http://www.open.edu/openlearncreate/mod/oucontent/view.php?id=80328",
          "title": "OLCreate: TESSA_Eng Key Resource: Using role play/dialogue/drama in the classroom",
          "children": [],
          "original_url": "http://www.open.edu/openlearnworks/mod/oucontent/view.php?id=80328"
        },
        {
          "kind": "oucontent",
          "url": "http://www.open.edu/openlearncreate/mod/oucontent/view.php?id=80329",
          "title": "OLCreate: TESSA_Eng Key Resource: Using storytelling in the classroom",
          "children": [],
          "original_url": "http://www.open.edu/openlearnworks/mod/oucontent/view.php?id=80329"
        },
        {
          "kind": "oucontent",
          "url": "http://www.open.edu/openlearncreate/mod/oucontent/view.php?id=82493",
          "title": "OLCreate: TESSA_Eng Key Resource: Using new technologies",
          "children": [],
          "original_url": "http://www.open.edu/openlearnworks/mod/oucontent/view.php?id=82493"
        },
        {
          "kind": "oucontent",
          "url": "http://www.open.edu/openlearncreate/mod/oucontent/view.php?id=83251",
          "title": "OLCreate: TESSA_Eng Key Resource: Working with multigrade classes",
          "children": [],
          "original_url": "http://www.open.edu/openlearnworks/mod/oucontent/view.php?id=83251"
        }
      ]
    },
    {
      "kind": "subpage",
      "url": "http://www.open.edu/openlearncreate/mod/subpage/view.php?id=81258",
      "title": "OLCreate: TESSA_ARABIC: \u0643\u062a\u064a\u0628\u0627\u062a \u0648\u0645\u062c\u0645\u0648\u0639\u0629 \u0645\u0646 \u0628\u0631\u0627\u0645\u062c \u0648\u0623\u062f\u0648\u0627\u062a \u062a\u0637\u0648\u064a\u0631 \u0627\u0644\u0645\u0639\u0644\u0645\u064a\u0646 \u0648\u0627\u0644\u0645\u0633\u0624\u0648\u0644\u064a\u0646 \u0639\u0646 \u062a\u0639\u0644\u064a\u0645\u0647\u0645",
      "children": [
        {
          "kind": "subpage",
          "url": "http://www.open.edu/openlearncreate/mod/subpage/view.php?id=81299",
          "title": "OLCreate: TESSA_ARABIC: \u0627\u0644\u0635\u0641\u062d\u0629 \u0627\u0644\u0641\u0631\u0639\u064a\u0629 \u0644\u0645\u062c\u0645\u0648\u0639\u0629 \u0628\u0631\u0627\u0645\u062c \u0648\u0623\u062f\u0648\u0627\u062a \u0627\u0644\u062a\u0637\u0648\u064a\u0631 \u0644\u0644\u0645\u0634\u0631\u0641\u064a\u0646 \u0639\u0644\u0649 \u0645\u0645\u0627\u0631\u0633\u0629 \u0627\u0644\u062a\u062f\u0631\u064a\u0633",
          "children": [
            {
              "kind": "subpage",
              "url": "http://www.open.edu/openlearncreate/mod/subpage/view.php?id=81258",
              "title": "OLCreate: TESSA_ARABIC: \u0643\u062a\u064a\u0628\u0627\u062a \u0648\u0645\u062c\u0645\u0648\u0639\u0629 \u0645\u0646 \u0628\u0631\u0627\u0645\u062c \u0648\u0623\u062f\u0648\u0627\u062a \u062a\u0637\u0648\u064a\u0631 \u0627\u0644\u0645\u0639\u0644\u0645\u064a\u0646 \u0648\u0627\u0644\u0645\u0633\u0624\u0648\u0644\u064a\u0646 \u0639\u0646 \u062a\u0639\u0644\u064a\u0645\u0647\u0645",
              "children": [],
              "original_url": "http://www.open.edu/openlearnworks/mod/subpage/view.php?id=81258"
            }
          ]
        },
        {
          "kind": "subpage",
          "url": "http://www.open.edu/openlearncreate/mod/subpage/view.php?id=81298",
          "title": "OLCreate: TESSA_ARABIC: \u0627\u0644\u0635\u0641\u062d\u0629 \u0627\u0644\u0641\u0631\u0639\u064a\u0629 \u0644\u0645\u062c\u0645\u0648\u0639\u0629 \u0628\u0631\u0627\u0645\u062c \u0648\u0623\u062f\u0648\u0627\u062a \u062a\u0637\u0648\u064a\u0631 \u0627\u0644\u062a\u0639\u0644\u064a\u0645 \u0627\u0644\u0634\u0627\u0645\u0644\u0629",
          "children": []
        }
      ]
    },
    {
      "kind": "subpage",
      "url": "http://www.open.edu/openlearncreate/mod/subpage/view.php?id=81259",
      "title": "OLCreate: TESSA_ARABIC: \u0645\u0648\u0627\u0631\u062f \u0635\u0648\u062a\u064a\u0629",
      "children": [
        {
          "kind": "subpage",
          "url": "http://www.open.edu/openlearncreate/mod/subpage/view.php?id=81310",
          "title": "OLCreate: TESSA_ARABIC: \u0627\u0644\u062a\u0639\u0644\u0645 \u0627\u0644\u0641\u0639\u0627\u0644",
          "children": [
            {
              "kind": "resource",
              "url": "http://www.open.edu/openlearncreate/mod/resource/view.php?id=81325",
              "title": "OLCreate: TESSA_ARABIC: \u062a\u0646\u0632\u064a\u0644 \u0627\u0644\u0645\u0648\u0627\u0631\u062f \u0627\u0644\u0635\u0648\u062a\u064a\u0629",
              "children": []
            },
            {
              "kind": "NoDownloadWebResource",
              "url": "http://www.open.edu/openlearncreate/pluginfile.php/173007/mod_resource/content/1/castthespell_transcript.pdf",
              "children": [],
              "content-type": "application/pdf"
            },
            {
              "kind": "NoDownloadWebResource",
              "url": "http://www.open.edu/openlearncreate/pluginfile.php/173008/mod_resource/content/1/castthespell_synopsis.pdf",
              "children": [],
              "content-type": "application/pdf"
            },
            {
              "kind": "resource",
              "url": "http://www.open.edu/openlearncreate/mod/resource/view.php?id=81328",
              "title": "OLCreate: TESSA_ARABIC: \u062a\u0646\u0632\u064a\u0644 \u0627\u0644\u0645\u0648\u0627\u0631\u062f \u0627\u0644\u0635\u0648\u062a\u064a\u0629",
              "children": []
            },
            {
              "kind": "NoDownloadWebResource",
              "url": "http://www.open.edu/openlearncreate/pluginfile.php/173010/mod_resource/content/1/sevenrivers_transcript.pdf",
              "children": [],
              "content-type": "application/pdf"
            },
            {
              "kind": "NoDownloadWebResource",
              "url": "http://www.open.edu/openlearncreate/pluginfile.php/173011/mod_resource/content/1/sevenrivers_synopsis.pdf",
              "children": [],
              "content-type": "application/pdf"
            },
            {
              "kind": "resource",
              "url": "http://www.open.edu/openlearncreate/mod/resource/view.php?id=81331",
              "title": "OLCreate: TESSA_ARABIC: \u062a\u0646\u0632\u064a\u0644 \u0627\u0644\u0645\u0648\u0627\u0631\u062f \u0627\u0644\u0635\u0648\u062a\u064a\u0629",
              "children": []
            },
            {
              "kind": "NoDownloadWebResource",
              "url": "http://www.open.edu/openlearncreate/pluginfile.php/173013/mod_resource/content/1/mathsgame_transcript.pdf",
              "children": [],
              "content-type": "application/pdf"
            },
            {
              "kind": "NoDownloadWebResource",
              "url": "http://www.open.edu/openlearncreate/pluginfile.php/173014/mod_resource/content/1/mathsgame_synopsis.pdf",
              "children": [],
              "content-type": "application/pdf"
            },
            {
              "kind": "resource",
              "url": "http://www.open.edu/openlearncreate/mod/resource/view.php?id=81334",
              "title": "OLCreate: TESSA_ARABIC: \u062a\u0646\u0632\u064a\u0644 \u0627\u0644\u0645\u0648\u0627\u0631\u062f \u0627\u0644\u0635\u0648\u062a\u064a\u0629",
              "children": []
            },
            {
              "kind": "NoDownloadWebResource",
              "url": "http://www.open.edu/openlearncreate/pluginfile.php/173016/mod_resource/content/1/openday_transcript.pdf",
              "children": [],
              "content-type": "application/pdf"
            },
            {
              "kind": "NoDownloadWebResource",
              "url": "http://www.open.edu/openlearncreate/pluginfile.php/173017/mod_resource/content/1/openday_synopsis.pdf",
              "children": [],
              "content-type": "application/pdf"
            },
            {
              "kind": "resource",
              "url": "http://www.open.edu/openlearncreate/mod/resource/view.php?id=81338",
              "title": "OLCreate: TESSA_ARABIC: \u062a\u0646\u0632\u064a\u0644 \u0627\u0644\u0645\u0648\u0627\u0631\u062f \u0627\u0644\u0635\u0648\u062a\u064a\u0629",
              "children": []
            },
            {
              "kind": "NoDownloadWebResource",
              "url": "http://www.open.edu/openlearncreate/pluginfile.php/173027/mod_resource/content/1/townmeeting_transcript.pdf",
              "children": [],
              "content-type": "application/pdf"
            },
            {
              "kind": "NoDownloadWebResource",
              "url": "http://www.open.edu/openlearncreate/pluginfile.php/173029/mod_resource/content/1/townmeeting_synopsis.pdf",
              "children": [],
              "content-type": "application/pdf"
            },
            {
              "kind": "resource",
              "url": "http://www.open.edu/openlearncreate/mod/resource/view.php?id=81341",
              "title": "OLCreate: TESSA_ARABIC: \u062a\u0646\u0632\u064a\u0644 \u0627\u0644\u0645\u0648\u0627\u0631\u062f \u0627\u0644\u0635\u0648\u062a\u064a\u0629",
              "children": []
            },
            {
              "kind": "NoDownloadWebResource",
              "url": "http://www.open.edu/openlearncreate/pluginfile.php/173043/mod_resource/content/1/letmedocooking_transcript.pdf",
              "children": [],
              "content-type": "application/pdf"
            },
            {
              "kind": "NoDownloadWebResource",
              "url": "http://www.open.edu/openlearncreate/pluginfile.php/173044/mod_resource/content/1/cooking_synopsis.pdf",
              "children": [],
              "content-type": "application/pdf"
            },
            {
              "kind": "subpage",
              "url": "http://www.open.edu/openlearncreate/mod/subpage/view.php?id=81259",
              "title": "OLCreate: TESSA_ARABIC: \u0645\u0648\u0627\u0631\u062f \u0635\u0648\u062a\u064a\u0629",
              "children": [],
              "original_url": "http://www.open.edu/openlearnworks/mod/subpage/view.php?id=81259"
            }
          ]
        },
        {
          "kind": "subpage",
          "url": "http://www.open.edu/openlearncreate/mod/subpage/view.php?id=81311",
          "title": "OLCreate: TESSA_ARABIC: \u0643\u064a\u0641\u064a\u0629 \u0627\u0644\u0639\u0645\u0644 \u0627\u0644\u0645\u0647\u0646\u064a \u0627\u0644\u0645\u062a\u062e\u0635\u0635",
          "children": [
            {
              "kind": "resource",
              "url": "http://www.open.edu/openlearncreate/mod/resource/view.php?id=81370",
              "title": "OLCreate: TESSA_ARABIC: \u062a\u0646\u0632\u064a\u0644 \u0627\u0644\u0645\u0648\u0627\u0631\u062f \u0627\u0644\u0635\u0648\u062a\u064a\u0629",
              "children": []
            },
            {
              "kind": "NoDownloadWebResource",
              "url": "http://www.open.edu/openlearncreate/pluginfile.php/173750/mod_resource/content/1/showgoon_transcript.pdf",
              "children": [],
              "content-type": "application/pdf"
            },
            {
              "kind": "NoDownloadWebResource",
              "url": "http://www.open.edu/openlearncreate/pluginfile.php/173751/mod_resource/content/1/showmustgo_synopsis.pdf",
              "children": [],
              "content-type": "application/pdf"
            },
            {
              "kind": "resource",
              "url": "http://www.open.edu/openlearncreate/mod/resource/view.php?id=81373",
              "title": "OLCreate: TESSA_ARABIC: \u062a\u0646\u0632\u064a\u0644 \u0627\u0644\u0645\u0648\u0627\u0631\u062f \u0627\u0644\u0635\u0648\u062a\u064a\u0629",
              "children": []
            },
            {
              "kind": "NoDownloadWebResource",
              "url": "http://www.open.edu/openlearncreate/pluginfile.php/173747/mod_resource/content/3/viva_transcript.pdf",
              "children": [],
              "content-type": "application/pdf"
            },
            {
              "kind": "NoDownloadWebResource",
              "url": "http://www.open.edu/openlearncreate/pluginfile.php/173748/mod_resource/content/1/viva_synopsis.pdf",
              "children": [],
              "content-type": "application/pdf"
            }
          ]
        },
        {
          "kind": "subpage",
          "url": "http://www.open.edu/openlearncreate/mod/subpage/view.php?id=81312",
          "title": "OLCreate: TESSA_ARABIC: \u0627\u0644\u062a\u0639\u0627\u0645\u0644 \u0645\u0639 \u0627\u0644\u0645\u0648\u0636\u0648\u0639\u0627\u062a \u0627\u0644\u062d\u0633\u0627\u0633\u0629",
          "children": [
            {
              "kind": "resource",
              "url": "http://www.open.edu/openlearncreate/mod/resource/view.php?id=81380",
              "title": "OLCreate: TESSA_ARABIC: \u062a\u0646\u0632\u064a\u0644 \u0627\u0644\u0645\u0648\u0627\u0631\u062f \u0627\u0644\u0635\u0648\u062a\u064a\u0629",
              "children": []
            },
            {
              "kind": "NoDownloadWebResource",
              "url": "http://www.open.edu/openlearncreate/pluginfile.php/173757/mod_resource/content/1/adjua_transcript.pdf",
              "children": [],
              "content-type": "application/pdf"
            },
            {
              "kind": "NoDownloadWebResource",
              "url": "http://www.open.edu/openlearncreate/pluginfile.php/173758/mod_resource/content/1/adjua_synopsis.pdf",
              "children": [],
              "content-type": "application/pdf"
            },
            {
              "kind": "resource",
              "url": "http://www.open.edu/openlearncreate/mod/resource/view.php?id=81383",
              "title": "OLCreate: TESSA_ARABIC: \u062a\u0646\u0632\u064a\u0644 \u0627\u0644\u0645\u0648\u0627\u0631\u062f \u0627\u0644\u0635\u0648\u062a\u064a\u0629",
              "children": []
            },
            {
              "kind": "NoDownloadWebResource",
              "url": "http://www.open.edu/openlearncreate/pluginfile.php/173769/mod_resource/content/1/notorious_transcript.pdf",
              "children": [],
              "content-type": "application/pdf"
            },
            {
              "kind": "NoDownloadWebResource",
              "url": "http://www.open.edu/openlearncreate/pluginfile.php/173770/mod_resource/content/1/notorious_synopsis.pdf",
              "children": [],
              "content-type": "application/pdf"
            },
            {
              "kind": "resource",
              "url": "http://www.open.edu/openlearncreate/mod/resource/view.php?id=81386",
              "title": "OLCreate: TESSA_ARABIC: \u062a\u0646\u0632\u064a\u0644 \u0627\u0644\u0645\u0648\u0627\u0631\u062f \u0627\u0644\u0635\u0648\u062a\u064a\u0629",
              "children": []
            },
            {
              "kind": "NoDownloadWebResource",
              "url": "http://www.open.edu/openlearncreate/pluginfile.php/173772/mod_resource/content/1/chase_transcript.pdf",
              "children": [],
              "content-type": "application/pdf"
            },
            {
              "kind": "NoDownloadWebResource",
              "url": "http://www.open.edu/openlearncreate/pluginfile.php/173773/mod_resource/content/1/chase_synopsis.pdf",
              "children": [],
              "content-type": "application/pdf"
            },
            {
              "kind": "resource",
              "url": "http://www.open.edu/openlearncreate/mod/resource/view.php?id=81389",
              "title": "OLCreate: TESSA_ARABIC: \u062a\u0646\u0632\u064a\u0644 \u0627\u0644\u0645\u0648\u0627\u0631\u062f \u0627\u0644\u0635\u0648\u062a\u064a\u0629",
              "children": []
            },
            {
              "kind": "NoDownloadWebResource",
              "url": "http://www.open.edu/openlearncreate/pluginfile.php/173775/mod_resource/content/1/babies_transcript.pdf",
              "children": [],
              "content-type": "application/pdf"
            },
            {
              "kind": "NoDownloadWebResource",
              "url": "http://www.open.edu/openlearncreate/pluginfile.php/173776/mod_resource/content/1/babies_synopsis.pdf",
              "children": [],
              "content-type": "application/pdf"
            }
          ]
        },
        {
          "kind": "subpage",
          "url": "http://www.open.edu/openlearncreate/mod/subpage/view.php?id=109814",
          "title": "OLCreate: TESSA_ARABIC: \u0641\u0631\u0635 \u0645\u062a\u0633\u0627\u0648\u064a\u0629",
          "children": [
            {
              "kind": "NoDownloadWebResource",
              "url": "http://www.open.edu/openlearncreate/pluginfile.php/228147/mod_resource/content/1/01%20Public%20holiday.mp3?forcedownload=1",
              "children": [],
              "content-type": "audio/mp3"
            },
            {
              "kind": "NoDownloadWebResource",
              "url": "http://www.open.edu/openlearncreate/pluginfile.php/228148/mod_resource/content/1/01%20Public%20holiday_transcript.pdf?forcedownload=1",
              "children": [],
              "content-type": "application/pdf"
            },
            {
              "kind": "NoDownloadWebResource",
              "url": "http://www.open.edu/openlearncreate/pluginfile.php/228149/mod_resource/content/1/01%20Public%20holiday_synopsis.pdf?forcedownload=1",
              "children": [],
              "content-type": "application/pdf"
            },
            {
              "kind": "NoDownloadWebResource",
              "url": "http://www.open.edu/openlearncreate/pluginfile.php/228150/mod_resource/content/1/02%20Seeking%20help.mp3?forcedownload=1",
              "children": [],
              "content-type": "audio/mp3"
            },
            {
              "kind": "NoDownloadWebResource",
              "url": "http://www.open.edu/openlearncreate/pluginfile.php/228152/mod_resource/content/1/02%20Seeking%20help_transcript.pdf?forcedownload=1",
              "children": [],
              "content-type": "application/pdf"
            },
            {
              "kind": "NoDownloadWebResource",
              "url": "http://www.open.edu/openlearncreate/pluginfile.php/228153/mod_resource/content/1/02%20Seeking%20help_synopsis.pdf?forcedownload=1",
              "children": [],
              "content-type": "application/pdf"
            },
            {
              "kind": "NoDownloadWebResource",
              "url": "http://www.open.edu/openlearncreate/pluginfile.php/228154/mod_resource/content/1/03%20Smart%20father.mp3?forcedownload=1",
              "children": [],
              "content-type": "audio/mp3"
            },
            {
              "kind": "NoDownloadWebResource",
              "url": "http://www.open.edu/openlearncreate/pluginfile.php/228155/mod_resource/content/1/03%20Smart%20father_transcript.pdf?forcedownload=1",
              "children": [],
              "content-type": "application/pdf"
            },
            {
              "kind": "NoDownloadWebResource",
              "url": "http://www.open.edu/openlearncreate/pluginfile.php/228156/mod_resource/content/1/03%20Smart%20father_synopsis.pdf?forcedownload=1",
              "children": [],
              "content-type": "application/pdf"
            },
            {
              "kind": "NoDownloadWebResource",
              "url": "http://www.open.edu/openlearncreate/pluginfile.php/228157/mod_resource/content/1/04%20The%20lost%20boy.mp3?forcedownload=1",
              "children": [],
              "content-type": "audio/mp3"
            },
            {
              "kind": "NoDownloadWebResource",
              "url": "http://www.open.edu/openlearncreate/pluginfile.php/228158/mod_resource/content/1/04%20The%20lost%20boy_transcript.pdf?forcedownload=1",
              "children": [],
              "content-type": "application/pdf"
            },
            {
              "kind": "NoDownloadWebResource",
              "url": "http://www.open.edu/openlearncreate/pluginfile.php/228159/mod_resource/content/1/04%20The%20lost%20boy_synopsis.pdf?forcedownload=1",
              "children": [],
              "content-type": "application/pdf"
            },
            {
              "kind": "NoDownloadWebResource",
              "url": "http://www.open.edu/openlearncreate/pluginfile.php/228160/mod_resource/content/1/08_keep_your_mouth_shut.mp3.mp3?forcedownload=1",
              "children": [],
              "content-type": "audio/mp3"
            },
            {
              "kind": "NoDownloadWebResource",
              "url": "http://www.open.edu/openlearncreate/pluginfile.php/228161/mod_resource/content/1/keepmouthshut_transcript.pdf?forcedownload=1",
              "children": [],
              "content-type": "application/pdf"
            },
            {
              "kind": "NoDownloadWebResource",
              "url": "http://www.open.edu/openlearncreate/pluginfile.php/228162/mod_resource/content/1/keepmouthshut_synopsis.pdf?forcedownload=1",
              "children": [],
              "content-type": "application/pdf"
            }
          ]
        },
        {
          "kind": "subpage",
          "url": "http://www.open.edu/openlearncreate/mod/subpage/view.php?id=81314",
          "title": "OLCreate: TESSA_ARABIC: \u0627\u0644\u0627\u0633\u062a\u0645\u0627\u0639 \u0625\u0644\u0649 \u0627\u0644\u0637\u0644\u0627\u0628",
          "children": [
            {
              "kind": "resource",
              "url": "http://www.open.edu/openlearncreate/mod/resource/view.php?id=81401",
              "title": "OLCreate: TESSA_ARABIC: \u062a\u0646\u0632\u064a\u0644 \u0627\u0644\u0645\u0648\u0627\u0631\u062f \u0627\u0644\u0635\u0648\u062a\u064a\u0629",
              "children": []
            },
            {
              "kind": "NoDownloadWebResource",
              "url": "http://www.open.edu/openlearncreate/pluginfile.php/173799/mod_resource/content/1/becareful_transcript.pdf",
              "children": [],
              "content-type": "application/pdf"
            },
            {
              "kind": "NoDownloadWebResource",
              "url": "http://www.open.edu/openlearncreate/pluginfile.php/173800/mod_resource/content/1/becareful_synopsis.pdf",
              "children": [],
              "content-type": "application/pdf"
            },
            {
              "kind": "resource",
              "url": "http://www.open.edu/openlearncreate/mod/resource/view.php?id=81404",
              "title": "OLCreate: TESSA_ARABIC: \u062a\u0646\u0632\u064a\u0644 \u0627\u0644\u0645\u0648\u0627\u0631\u062f \u0627\u0644\u0635\u0648\u062a\u064a\u0629",
              "children": []
            },
            {
              "kind": "NoDownloadWebResource",
              "url": "http://www.open.edu/openlearncreate/pluginfile.php/173802/mod_resource/content/1/catchthief_transcript.pdf",
              "children": [],
              "content-type": "application/pdf"
            },
            {
              "kind": "NoDownloadWebResource",
              "url": "http://www.open.edu/openlearncreate/pluginfile.php/173803/mod_resource/content/1/catchthethief_synopsis.pdf",
              "children": [],
              "content-type": "application/pdf"
            },
            {
              "kind": "resource",
              "url": "http://www.open.edu/openlearncreate/mod/resource/view.php?id=81407",
              "title": "OLCreate: TESSA_ARABIC: \u062a\u0646\u0632\u064a\u0644 \u0627\u0644\u0645\u0648\u0627\u0631\u062f \u0627\u0644\u0635\u0648\u062a\u064a\u0629",
              "children": []
            },
            {
              "kind": "NoDownloadWebResource",
              "url": "http://www.open.edu/openlearncreate/pluginfile.php/173805/mod_resource/content/1/somethinggood_transcript.pdf",
              "children": [],
              "content-type": "application/pdf"
            },
            {
              "kind": "NoDownloadWebResource",
              "url": "http://www.open.edu/openlearncreate/pluginfile.php/173806/mod_resource/content/1/somethinggood_synopsis.pdf",
              "children": [],
              "content-type": "application/pdf"
            },
            {
              "kind": "resource",
              "url": "http://www.open.edu/openlearncreate/mod/resource/view.php?id=81410",
              "title": "OLCreate: TESSA_ARABIC: \u062a\u0646\u0632\u064a\u0644 \u0627\u0644\u0645\u0648\u0627\u0631\u062f \u0627\u0644\u0635\u0648\u062a\u064a\u0629",
              "children": []
            },
            {
              "kind": "NoDownloadWebResource",
              "url": "http://www.open.edu/openlearncreate/pluginfile.php/173808/mod_resource/content/1/eyewitness_transcript.pdf",
              "children": [],
              "content-type": "application/pdf"
            },
            {
              "kind": "NoDownloadWebResource",
              "url": "http://www.open.edu/openlearncreate/pluginfile.php/173809/mod_resource/content/1/eyewitness_synopsis.pdf",
              "children": [],
              "content-type": "application/pdf"
            }
          ]
        },
        {
          "kind": "subpage",
          "url": "http://www.open.edu/openlearncreate/mod/subpage/view.php?id=81315",
          "title": "OLCreate: TESSA_ARABIC: \u062a\u062d\u0641\u064a\u0632 \u0627\u0644\u0637\u0644\u0627\u0628",
          "children": [
            {
              "kind": "resource",
              "url": "http://www.open.edu/openlearncreate/mod/resource/view.php?id=81416",
              "title": "OLCreate: TESSA_ARABIC: \u062a\u0646\u0632\u064a\u0644 \u0627\u0644\u0645\u0648\u0627\u0631\u062f \u0627\u0644\u0635\u0648\u062a\u064a\u0629",
              "children": []
            },
            {
              "kind": "NoDownloadWebResource",
              "url": "http://www.open.edu/openlearncreate/pluginfile.php/173815/mod_resource/content/1/anythingforschool_transcript.pdf",
              "children": [],
              "content-type": "application/pdf"
            },
            {
              "kind": "NoDownloadWebResource",
              "url": "http://www.open.edu/openlearncreate/pluginfile.php/173816/mod_resource/content/1/anythingforschool_synopsis.pdf",
              "children": [],
              "content-type": "application/pdf"
            },
            {
              "kind": "resource",
              "url": "http://www.open.edu/openlearncreate/mod/resource/view.php?id=81419",
              "title": "OLCreate: TESSA_ARABIC: \u062a\u0646\u0632\u064a\u0644 \u0627\u0644\u0645\u0648\u0627\u0631\u062f \u0627\u0644\u0635\u0648\u062a\u064a\u0629",
              "children": []
            },
            {
              "kind": "NoDownloadWebResource",
              "url": "http://www.open.edu/openlearncreate/pluginfile.php/173820/mod_resource/content/1/plaintain_transcript.pdf",
              "children": [],
              "content-type": "application/pdf"
            },
            {
              "kind": "NoDownloadWebResource",
              "url": "http://www.open.edu/openlearncreate/pluginfile.php/173821/mod_resource/content/1/plaintainseller_synopsis.pdf",
              "children": [],
              "content-type": "application/pdf"
            },
            {
              "kind": "resource",
              "url": "http://www.open.edu/openlearncreate/mod/resource/view.php?id=81422",
              "title": "OLCreate: TESSA_ARABIC: \u062a\u0646\u0632\u064a\u0644 \u0627\u0644\u0645\u0648\u0627\u0631\u062f \u0627\u0644\u0635\u0648\u062a\u064a\u0629",
              "children": []
            },
            {
              "kind": "NoDownloadWebResource",
              "url": "http://www.open.edu/openlearncreate/pluginfile.php/173823/mod_resource/content/1/musicteacher_transcript.pdf",
              "children": [],
              "content-type": "application/pdf"
            },
            {
              "kind": "NoDownloadWebResource",
              "url": "http://www.open.edu/openlearncreate/pluginfile.php/173824/mod_resource/content/1/musicteacher_synopsis.pdf",
              "children": [],
              "content-type": "application/pdf"
            }
          ]
        },
        {
          "kind": "subpage",
          "url": "http://www.open.edu/openlearncreate/mod/subpage/view.php?id=81316",
          "title": "OLCreate: TESSA_ARABIC: \u0627\u0633\u062a\u062e\u062f\u0627\u0645 \u0627\u0644\u0644\u063a\u0629 \u0627\u0644\u0645\u0646\u0627\u0633\u0628\u0629",
          "children": [
            {
              "kind": "resource",
              "url": "http://www.open.edu/openlearncreate/mod/resource/view.php?id=81427",
              "title": "OLCreate: TESSA_ARABIC: \u062a\u0646\u0632\u064a\u0644 \u0627\u0644\u0645\u0648\u0627\u0631\u062f \u0627\u0644\u0635\u0648\u062a\u064a\u0629",
              "children": []
            },
            {
              "kind": "NoDownloadWebResource",
              "url": "http://www.open.edu/openlearncreate/pluginfile.php/173829/mod_resource/content/1/thief_transcript.pdf",
              "children": [],
              "content-type": "application/pdf"
            },
            {
              "kind": "NoDownloadWebResource",
              "url": "http://www.open.edu/openlearncreate/pluginfile.php/173830/mod_resource/content/1/thief_synopsis.pdf",
              "children": [],
              "content-type": "application/pdf"
            },
            {
              "kind": "resource",
              "url": "http://www.open.edu/openlearncreate/mod/resource/view.php?id=81430",
              "title": "OLCreate: TESSA_ARABIC: \u062a\u0646\u0632\u064a\u0644 \u0627\u0644\u0645\u0648\u0627\u0631\u062f \u0627\u0644\u0635\u0648\u062a\u064a\u0629",
              "children": []
            },
            {
              "kind": "NoDownloadWebResource",
              "url": "http://www.open.edu/openlearncreate/pluginfile.php/173832/mod_resource/content/1/walking_transcript.pdf",
              "children": [],
              "content-type": "application/pdf"
            },
            {
              "kind": "NoDownloadWebResource",
              "url": "http://www.open.edu/openlearncreate/pluginfile.php/173834/mod_resource/content/1/walking_synopsis.pdf",
              "children": [],
              "content-type": "application/pdf"
            }
          ]
        },
        {
          "kind": "subpage",
          "url": "http://www.open.edu/openlearncreate/mod/subpage/view.php?id=81317",
          "title": "OLCreate: TESSA_ARABIC: \u0627\u0633\u062a\u062e\u062f\u0627\u0645 \u0627\u0644\u0645\u0648\u0627\u0631\u062f \u0627\u0644\u0645\u062d\u0644\u064a\u0629",
          "children": [
            {
              "kind": "resource",
              "url": "http://www.open.edu/openlearncreate/mod/resource/view.php?id=81437",
              "title": "OLCreate: TESSA_ARABIC: \u062a\u0646\u0632\u064a\u0644 \u0627\u0644\u0645\u0648\u0627\u0631\u062f \u0627\u0644\u0635\u0648\u062a\u064a\u0629",
              "children": []
            },
            {
              "kind": "NoDownloadWebResource",
              "url": "http://www.open.edu/openlearncreate/pluginfile.php/173841/mod_resource/content/1/excursion_transcript.pdf",
              "children": [],
              "content-type": "application/pdf"
            },
            {
              "kind": "NoDownloadWebResource",
              "url": "http://www.open.edu/openlearncreate/pluginfile.php/173842/mod_resource/content/1/excursion_synopsis.pdf",
              "children": [],
              "content-type": "application/pdf"
            },
            {
              "kind": "resource",
              "url": "http://www.open.edu/openlearncreate/mod/resource/view.php?id=81440",
              "title": "OLCreate: TESSA_ARABIC: \u062a\u0646\u0632\u064a\u0644 \u0627\u0644\u0645\u0648\u0627\u0631\u062f \u0627\u0644\u0635\u0648\u062a\u064a\u0629",
              "children": []
            },
            {
              "kind": "NoDownloadWebResource",
              "url": "http://www.open.edu/openlearncreate/pluginfile.php/173844/mod_resource/content/1/kiteforrent_transcript.pdf",
              "children": [],
              "content-type": "application/pdf"
            },
            {
              "kind": "NoDownloadWebResource",
              "url": "http://www.open.edu/openlearncreate/pluginfile.php/173845/mod_resource/content/1/excursion_synopsis.pdf",
              "children": [],
              "content-type": "application/pdf"
            },
            {
              "kind": "resource",
              "url": "http://www.open.edu/openlearncreate/mod/resource/view.php?id=81443",
              "title": "OLCreate: TESSA_ARABIC: \u062a\u0646\u0632\u064a\u0644 \u0627\u0644\u0645\u0648\u0627\u0631\u062f \u0627\u0644\u0635\u0648\u062a\u064a\u0629",
              "children": []
            },
            {
              "kind": "NoDownloadWebResource",
              "url": "http://www.open.edu/openlearncreate/pluginfile.php/173847/mod_resource/content/1/nohidingplace_transcript.pdf",
              "children": [],
              "content-type": "application/pdf"
            },
            {
              "kind": "NoDownloadWebResource",
              "url": "http://www.open.edu/openlearncreate/pluginfile.php/173848/mod_resource/content/1/nohidingplace_synopsis.pdf",
              "children": [],
              "content-type": "application/pdf"
            },
            {
              "kind": "resource",
              "url": "http://www.open.edu/openlearncreate/mod/resource/view.php?id=81446",
              "title": "OLCreate: TESSA_ARABIC: \u062a\u0646\u0632\u064a\u0644 \u0627\u0644\u0645\u0648\u0627\u0631\u062f \u0627\u0644\u0635\u0648\u062a\u064a\u0629",
              "children": []
            },
            {
              "kind": "NoDownloadWebResource",
              "url": "http://www.open.edu/openlearncreate/pluginfile.php/173850/mod_resource/content/1/artwork_transcript.pdf",
              "children": [],
              "content-type": "application/pdf"
            },
            {
              "kind": "NoDownloadWebResource",
              "url": "http://www.open.edu/openlearncreate/pluginfile.php/173851/mod_resource/content/1/artwork_synopsis.pdf",
              "children": [],
              "content-type": "application/pdf"
            }
          ]
        }
      ]
    }
  ]
}